elasticrag/__init__.py
elasticrag/cli.py
elasticrag/client.py
elasticrag/collection.py
elasticrag/model.py
elasticrag/server.py
elasticrag/splitter.py
elasticrag/user.py
elasticrag/utils.py
elasticrag-0.3.2.dist-info/METADATA
elasticrag-0.3.2.dist-info/WHEEL
elasticrag-0.3.2.dist-info/entry_points.txt
elasticrag-0.3.2.dist-info/RECORD
