Metadata-Version: 2.4
Name: elasticrag
Version: 0.3.2
Summary: Elasticsearch-based RAG system with ingest pipeline processing
Project-URL: Homepage, https://github.com/lloydzhou/elasticrag
Project-URL: Repository, https://github.com/lloydzhou/elasticrag
Project-URL: Documentation, https://github.com/lloydzhou/elasticrag#readme
Project-URL: Issues, https://github.com/lloydzhou/elasticrag/issues
Author-email: Lloyd Zhou <lloydzhou@gmail.com>
License: MIT
Keywords: elasticsearch,embedding,nlp,rag,vector-search
Classifier: Development Status :: 4 - Beta
Classifier: Intended Audience :: Developers
Classifier: License :: OSI Approved :: MIT License
Classifier: Programming Language :: Python :: 3
Classifier: Programming Language :: Python :: 3.8
Classifier: Programming Language :: Python :: 3.9
Classifier: Programming Language :: Python :: 3.10
Classifier: Programming Language :: Python :: 3.11
Classifier: Programming Language :: Python :: 3.12
Classifier: Topic :: Database :: Database Engines/Servers
Classifier: Topic :: Scientific/Engineering :: Artificial Intelligence
Requires-Python: >=3.8
Requires-Dist: aiohttp>=3.10.11
Requires-Dist: elasticsearch>=8.0.0
Requires-Dist: python-dotenv>=1.0.0
Provides-Extra: all
Requires-Dist: black>=23.0.0; extra == 'all'
Requires-Dist: gradio>=4.44.1; extra == 'all'
Requires-Dist: isort>=5.12.0; extra == 'all'
Requires-Dist: pandas>=1.3.0; extra == 'all'
Requires-Dist: pytest-asyncio>=0.21.0; extra == 'all'
Requires-Dist: pytest>=7.0.0; extra == 'all'
Provides-Extra: dev
Requires-Dist: black>=23.0.0; extra == 'dev'
Requires-Dist: isort>=5.12.0; extra == 'dev'
Requires-Dist: pytest-asyncio>=0.21.0; extra == 'dev'
Requires-Dist: pytest>=7.0.0; extra == 'dev'
Provides-Extra: web
Requires-Dist: gradio>=4.44.1; extra == 'web'
Requires-Dist: pandas>=1.3.0; extra == 'web'
